gitdumper_tool/__init__.py
gitdumper_tool/__main__.py
gitdumper_tool/cli.py
gitdumper_tool/dumper.py
gitdumper_tool/logger.py
gitdumper_tool/utils.py
gitdumper_tool-0.1.1.dist-info/entry_points.txt
gitdumper_tool-0.1.1.dist-info/WHEEL
gitdumper_tool-0.1.1.dist-info/METADATA
gitdumper_tool-0.1.1.dist-info/RECORD
